uzbot/__init__.py
uzbot/uzbtelebot.py
uzbtelebot-0.0.8.dist-info/METADATA
uzbtelebot-0.0.8.dist-info/WHEEL
uzbtelebot-0.0.8.dist-info/top_level.txt
uzbtelebot-0.0.8.dist-info/RECORD
