Metadata-Version: 2.1
Name: uzbtelebot
Version: 0.0.8
Summary: Agar siz telegram bot yasashni beginner darajasida bo'lsangiz bu kutubxona siz uchun siz bu kutubxona orqali telegram bot yarata olasiz
Author: SalohiddinEsanbekov
Author-email: salohiddinsalohiddin123@gmail.com
Classifier: Programming Language :: Python :: 3
Classifier: License :: OSI Approved :: MIT License
Classifier: Operating System :: OS Independent
Requires-Dist: telebot
